tests/__init__.py
tests/test/__init__.py
tests/test/test_deep.py
vrypy/__init__.py
vrypy-0.3.dist-info/LICENSE
vrypy-0.3.dist-info/METADATA
vrypy-0.3.dist-info/WHEEL
vrypy-0.3.dist-info/top_level.txt
vrypy-0.3.dist-info/RECORD
