Metadata-Version: 2.1
Name: vrypy
Version: 0.3
Summary: Collection of Python utilities
Home-page: https://github.com/vojtarylko/vrypy
Author: Vojtech Rylko
Author-email: vojta.rylko@gmail.com
License: UNKNOWN
Platform: UNKNOWN
Classifier: Programming Language :: Python :: 3
Classifier: License :: OSI Approved :: MIT License
Classifier: Operating System :: OS Independent
